{
    "meta": {
        "total": 3215299,
        "last_update_at": "2022-06-18T21:14:38.084560+00:00"
    },
    "data": {
        "新北市": {
            "板橋區": 110725,
            "新莊區": 87042,
            "中和區": 86748,
            "三重區": 86239,
            "新店區": 54069,
            "土城區": 47899,
            "汐止區": 44540,
            "蘆洲區": 38510,
            "永和區": 37479,
            "樹林區": 33376,
            "淡水區": 28996,
            "三峽區": 19157,
            "五股區": 18349,
            "林口區": 18130,
            "鶯歌區": 16237,
            "泰山區": 15077,
            "八里區": 6745,
            "瑞芳區": 6150,
            "深坑區": 4791,
            "金山區": 2452,
            "三芝區": 2184,
            "萬里區": 2157,
            "烏來區": 677,
            "石碇區": 646,
            "貢寮區": 633,
            "石門區": 529,
            "雙溪區": 500,
            "坪林區": 381,
            "平溪區": 297,
            "其他": 0
        },
        "台北市": {
            "北投區": 35427,
            "文山區": 34945,
            "士林區": 34743,
            "內湖區": 34381,
            "萬華區": 31953,
            "信義區": 30371,
            "中山區": 29964,
            "大安區": 28275,
            "松山區": 22174,
            "大同區": 17862,
            "南港區": 17442,
            "中正區": 15482,
            "其他": 0
        },
        "桃園市": {
            "桃園區": 79873,
            "中壢區": 69750,
            "龜山區": 36793,
            "平鎮區": 36564,
            "八德區": 35505,
            "蘆竹區": 29360,
            "楊梅區": 28960,
            "龍潭區": 19445,
            "大溪區": 16551,
            "大園區": 14268,
            "觀音區": 12000,
            "新屋區": 7449,
            "復興區": 1763,
            "其他": 0
        },
        "彰化縣": {
            "彰化市": 27397,
            "員林市": 13372,
            "鹿港鎮": 13350,
            "和美鎮": 12636,
            "花壇鄉": 5639,
            "二林鎮": 5314,
            "福興鄉": 5078,
            "大村鄉": 5033,
            "溪湖鎮": 5017,
            "伸港鄉": 4602,
            "秀水鄉": 4120,
            "田中鎮": 4021,
            "社頭鄉": 3918,
            "埔心鄉": 3681,
            "北斗鎮": 3380,
            "永靖鄉": 3247,
            "芳苑鄉": 2948,
            "埔鹽鄉": 2747,
            "埤頭鄉": 2471,
            "溪州鄉": 2285,
            "芬園鄉": 2254,
            "田尾鄉": 2028,
            "線西鄉": 1984,
            "大城鄉": 1134,
            "二水鄉": 1113,
            "竹塘鄉": 932,
            "其他": 0
        },
        "基隆市": {
            "安樂區": 16568,
            "中正區": 10905,
            "信義區": 10896,
            "七堵區": 10781,
            "中山區": 8890,
            "仁愛區": 8172,
            "暖暖區": 7459,
            "其他": 1
        },
        "宜蘭縣": {
            "宜蘭市": 12983,
            "羅東鎮": 9694,
            "冬山鄉": 7632,
            "蘇澳鎮": 6573,
            "五結鄉": 5507,
            "礁溪鄉": 5220,
            "員山鄉": 4332,
            "頭城鎮": 3434,
            "壯圍鄉": 2866,
            "三星鄉": 2828,
            "南澳鄉": 2006,
            "大同鄉": 1432,
            "其他": 0
        },
        "台中市": {
            "北屯區": 31556,
            "西屯區": 30991,
            "大里區": 27436,
            "太平區": 25823,
            "南屯區": 20292,
            "北區": 18735,
            "豐原區": 17863,
            "南區": 15222,
            "沙鹿區": 14106,
            "大雅區": 12993,
            "潭子區": 12911,
            "西區": 12741,
            "清水區": 11092,
            "烏日區": 10667,
            "龍井區": 10286,
            "梧棲區": 10063,
            "東區": 9984,
            "霧峰區": 8947,
            "大甲區": 8726,
            "神岡區": 8271,
            "大肚區": 7244,
            "后里區": 5442,
            "東勢區": 4051,
            "外埔區": 3581,
            "中區": 2322,
            "大安區": 1985,
            "新社區": 1576,
            "石岡區": 1162,
            "和平區": 985,
            "其他": 0
        },
        "高雄市": {
            "鳳山區": 48537,
            "三民區": 41525,
            "楠梓區": 27546,
            "前鎮區": 24509,
            "小港區": 24290,
            "左營區": 22396,
            "苓雅區": 19254,
            "大寮區": 16847,
            "鼓山區": 15965,
            "岡山區": 13151,
            "仁武區": 12400,
            "林園區": 8454,
            "路竹區": 6731,
            "前金區": 6060,
            "燕巢區": 6031,
            "新興區": 5391,
            "梓官區": 5165,
            "大樹區": 4944,
            "鳥松區": 4917,
            "大社區": 4746,
            "橋頭區": 4624,
            "旗津區": 3695,
            "湖內區": 3599,
            "茄萣區": 3569,
            "阿蓮區": 3048,
            "旗山區": 2968,
            "鹽埕區": 2465,
            "美濃區": 2389,
            "彌陀區": 2381,
            "永安區": 1321,
            "內門區": 965,
            "杉林區": 893,
            "六龜區": 891,
            "桃源區": 601,
            "田寮區": 527,
            "那瑪夏區": 298,
            "甲仙區": 236,
            "茂林區": 224,
            "其他": 0
        },
        "屏東縣": {
            "屏東市": 23752,
            "東港鎮": 6749,
            "內埔鄉": 6355,
            "潮州鎮": 6328,
            "萬丹鄉": 6058,
            "新園鄉": 4370,
            "長治鄉": 3737,
            "恆春鎮": 3390,
            "鹽埔鄉": 2715,
            "里港鄉": 2642,
            "九如鄉": 2305,
            "枋寮鄉": 2305,
            "竹田鄉": 2276,
            "萬巒鄉": 1781,
            "高樹鄉": 1474,
            "佳冬鄉": 1325,
            "林邊鄉": 1325,
            "瑪家鄉": 1311,
            "來義鄉": 1176,
            "麟洛鄉": 1169,
            "泰武鄉": 1144,
            "三地門鄉": 1125,
            "崁頂鄉": 1114,
            "南州鄉": 854,
            "新埤鄉": 848,
            "春日鄉": 815,
            "琉球鄉": 761,
            "車城鄉": 615,
            "獅子鄉": 593,
            "牡丹鄉": 532,
            "滿州鄉": 457,
            "枋山鄉": 330,
            "霧台鄉": 216,
            "其他": 0
        },
        "南投縣": {
            "南投市": 11277,
            "草屯鎮": 9473,
            "埔里鎮": 7172,
            "竹山鎮": 4676,
            "名間鄉": 3070,
            "仁愛鄉": 2118,
            "信義鄉": 1944,
            "國姓鄉": 1057,
            "鹿谷鄉": 1001,
            "水里鄉": 922,
            "中寮鄉": 774,
            "魚池鄉": 656,
            "集集鎮": 529,
            "其他": 0
        },
        "台南市": {
            "永康區": 33087,
            "安南區": 24665,
            "東區": 18478,
            "北區": 14767,
            "南區": 14692,
            "仁德區": 10165,
            "歸仁區": 8091,
            "中西區": 7747,
            "新營區": 7535,
            "安平區": 7322,
            "善化區": 6010,
            "新市區": 5410,
            "佳里區": 5268,
            "新化區": 5231,
            "關廟區": 4502,
            "麻豆區": 4181,
            "安定區": 3331,
            "西港區": 2332,
            "柳營區": 2281,
            "鹽水區": 1997,
            "官田區": 1929,
            "六甲區": 1905,
            "學甲區": 1763,
            "下營區": 1760,
            "白河區": 1741,
            "七股區": 1695,
            "後壁區": 1503,
            "東山區": 1076,
            "玉井區": 1023,
            "將軍區": 881,
            "山上區": 841,
            "大內區": 609,
            "楠西區": 487,
            "北門區": 442,
            "南化區": 407,
            "左鎮區": 354,
            "龍崎區": 165,
            "其他": 0
        },
        "新竹市": {
            "東區": 30335,
            "北區": 18423,
            "香山區": 10944,
            "其他": 0
        },
        "新竹縣": {
            "竹北市": 26856,
            "湖口鄉": 16669,
            "竹東鎮": 14868,
            "新豐鄉": 8778,
            "新埔鎮": 3807,
            "關西鎮": 3344,
            "芎林鄉": 2339,
            "寶山鄉": 1809,
            "尖石鄉": 1366,
            "橫山鄉": 1327,
            "北埔鄉": 693,
            "五峰鄉": 615,
            "峨眉鄉": 361,
            "其他": 0
        },
        "雲林縣": {
            "斗六市": 10703,
            "虎尾鎮": 7535,
            "西螺鎮": 4670,
            "斗南鎮": 3665,
            "麥寮鄉": 2913,
            "北港鎮": 2545,
            "莿桐鄉": 2248,
            "古坑鄉": 2081,
            "土庫鎮": 1888,
            "崙背鄉": 1765,
            "二崙鄉": 1613,
            "元長鄉": 1502,
            "林內鄉": 1303,
            "大埤鄉": 1166,
            "台西鄉": 1150,
            "口湖鄉": 1091,
            "四湖鄉": 954,
            "水林鄉": 948,
            "褒忠鄉": 815,
            "東勢鄉": 726,
            "其他": 0
        },
        "苗栗縣": {
            "頭份市": 13423,
            "竹南鎮": 13052,
            "苗栗市": 8442,
            "苑裡鎮": 5259,
            "後龍鎮": 3310,
            "通霄鎮": 3091,
            "公館鄉": 2483,
            "造橋鄉": 1972,
            "三義鄉": 1316,
            "銅鑼鄉": 1265,
            "卓蘭鎮": 1057,
            "頭屋鄉": 963,
            "南庄鄉": 926,
            "泰安鄉": 875,
            "大湖鄉": 795,
            "三灣鄉": 523,
            "西湖鄉": 303,
            "獅潭鄉": 196,
            "其他": 0
        },
        "花蓮縣": {
            "吉安鄉": 13509,
            "花蓮市": 13440,
            "秀林鄉": 4643,
            "玉里鎮": 4272,
            "新城鄉": 4257,
            "壽豐鄉": 2649,
            "光復鄉": 1573,
            "萬榮鄉": 1170,
            "鳳林鎮": 1165,
            "瑞穗鄉": 1154,
            "富里鄉": 1099,
            "卓溪鄉": 1088,
            "豐濱鄉": 467,
            "其他": 0
        },
        "嘉義市": {
            "西區": 13304,
            "東區": 10477,
            "其他": 0
        },
        "嘉義縣": {
            "民雄鄉": 7266,
            "水上鄉": 4718,
            "中埔鄉": 3555,
            "太保市": 3414,
            "朴子市": 3153,
            "大林鎮": 2746,
            "竹崎鄉": 2005,
            "新港鄉": 1964,
            "布袋鎮": 1337,
            "六腳鄉": 1224,
            "鹿草鄉": 1204,
            "梅山鄉": 984,
            "東石鄉": 982,
            "溪口鄉": 902,
            "義竹鄉": 745,
            "番路鄉": 608,
            "阿里山鄉": 402,
            "大埔鄉": 130,
            "其他": 0
        },
        "連江縣": {
            "南竿鄉": 601,
            "東引鄉": 203,
            "北竿鄉": 149,
            "莒光鄉": 83,
            "其他": 0
        },
        "金門縣": {
            "金湖鎮": 1121,
            "金城鎮": 1120,
            "金寧鄉": 1104,
            "金沙鎮": 562,
            "烈嶼鄉": 300,
            "烏坵鄉": 2,
            "其他": 0
        },
        "台東縣": {
            "台東市": 15274,
            "卑南鄉": 1900,
            "成功鎮": 1314,
            "太麻里鄉": 1093,
            "海端鄉": 777,
            "關山鎮": 771,
            "東河鄉": 731,
            "長濱鄉": 660,
            "蘭嶼鄉": 657,
            "鹿野鄉": 612,
            "延平鄉": 570,
            "池上鄉": 548,
            "金峰鄉": 397,
            "綠島鄉": 393,
            "大武鄉": 378,
            "達仁鄉": 252,
            "其他": 0
        },
        "澎湖縣": {
            "馬公市": 4630,
            "湖西鄉": 773,
            "白沙鄉": 409,
            "西嶼鄉": 291,
            "七美鄉": 84,
            "望安鄉": 78,
            "其他": 0
        }
    }
}